resolvelib/__init__.py
resolvelib/__init__.pyi
resolvelib/providers.py
resolvelib/providers.pyi
resolvelib/py.typed
resolvelib/reporters.py
resolvelib/reporters.pyi
resolvelib/resolvers.py
resolvelib/resolvers.pyi
resolvelib/structs.py
resolvelib/structs.pyi
resolvelib/compat/__init__.py
resolvelib/compat/collections_abc.py
resolvelib/compat/collections_abc.pyi
resolvelib-1.0.0.dist-info/LICENSE
resolvelib-1.0.0.dist-info/METADATA
resolvelib-1.0.0.dist-info/WHEEL
resolvelib-1.0.0.dist-info/top_level.txt
resolvelib-1.0.0.dist-info/RECORD
