Metadata-Version: 2.1
Name: resolvelib
Version: 1.0.0
Summary: Resolve abstract dependencies into concrete ones
Home-page: https://github.com/sarugaku/resolvelib
Author: Tzu-ping Chung
Author-email: uranusjr@gmail.com
License: ISC License
Keywords: dependency,resolution
Classifier: Development Status :: 3 - Alpha
Classifier: Intended Audience :: Developers
Classifier: License :: OSI Approved :: ISC License (ISCL)
Classifier: Operating System :: OS Independent
Classifier: Programming Language :: Python :: 2
Classifier: Programming Language :: Python :: 3
Classifier: Topic :: Software Development :: Libraries :: Python Modules
License-File: LICENSE
Provides-Extra: examples
Requires-Dist: html5lib ; extra == 'examples'
Requires-Dist: packaging ; extra == 'examples'
Requires-Dist: pygraphviz ; extra == 'examples'
Requires-Dist: requests ; extra == 'examples'
Provides-Extra: lint
Requires-Dist: black ; extra == 'lint'
Requires-Dist: flake8 ; extra == 'lint'
Requires-Dist: mypy ; extra == 'lint'
Requires-Dist: isort ; extra == 'lint'
Requires-Dist: types-requests ; extra == 'lint'
Provides-Extra: release
Requires-Dist: build ; extra == 'release'
Requires-Dist: towncrier ; extra == 'release'
Requires-Dist: twine ; extra == 'release'
Provides-Extra: test
Requires-Dist: commentjson ; extra == 'test'
Requires-Dist: packaging ; extra == 'test'
Requires-Dist: pytest ; extra == 'test'
